README.rst
setup.py
modtox/__init__.py
modtox/main.py
modtox.egg-info/PKG-INFO
modtox.egg-info/SOURCES.txt
modtox.egg-info/dependency_links.txt
modtox.egg-info/requires.txt
modtox.egg-info/top_level.txt
modtox/Helpers/__init__.py
modtox/Helpers/formats.py
modtox/Helpers/masks.py
modtox/Helpers/preprocess.py
modtox/ML/__init__.py
modtox/ML/classifiers.py
modtox/ML/descriptors_2D_ligand.py
modtox/ML/descriptors_MD.py
modtox/ML/domain.py
modtox/ML/dummy_regressor.py
modtox/ML/external_descriptors.py
modtox/ML/feature_selection.py
modtox/ML/model.py
modtox/ML/preprocess_data.py
modtox/ML/visualization.py
modtox/constants/__init__.py
modtox/constants/constants.py
modtox/cpptraj/__init__.py
modtox/cpptraj/analisis.py
modtox/data/__init__.py
modtox/data/databases.py
modtox/data/dude.py
modtox/data/gpcrdb.py
modtox/data/scrape_chembl/__init__.py
modtox/docking/__init__.py
modtox/docking/rDock.py
modtox/docking/glide/__init__.py
modtox/docking/glide/analyse.py
modtox/docking/glide/glide.py
tests/__init__.py
tests/test_platform.py