Metadata-Version: 1.0
Name: modtox
Version: 1.0.0.3
Summary: Asses toxic effect of drugs based on MD simualtions of HROT dataset
Home-page: https://github.com/NostrumBioDiscovery/modtox
Author: Daniel Soler
Author-email: daniel.soler@nostrumbiodiscovery.com
License: MIT
Platform: UNKNOWN
